prisma_web3_py/__init__.py
prisma_web3_py/base.py
prisma_web3_py/config.py
prisma_web3_py/database.py
prisma_web3_py/models/__init__.py
prisma_web3_py/models/ai_analysis_result.py
prisma_web3_py/models/crypto_news.py
prisma_web3_py/models/event_impacts.py
prisma_web3_py/models/event_labels.py
prisma_web3_py/models/groups.py
prisma_web3_py/models/news_semantic_dedup.py
prisma_web3_py/models/pre_signal.py
prisma_web3_py/models/signal.py
prisma_web3_py/models/token.py
prisma_web3_py/models/token_alias.py
prisma_web3_py/models/token_analysis_report.py
prisma_web3_py/models/token_metrics.py
prisma_web3_py/models/token_price_history.py
prisma_web3_py/models/token_price_monitor.py
prisma_web3_py/repositories/__init__.py
prisma_web3_py/repositories/ai_analysis_repository.py
prisma_web3_py/repositories/base_repository.py
prisma_web3_py/repositories/crypto_news_repository.py
prisma_web3_py/repositories/event_impact_repository.py
prisma_web3_py/repositories/event_labels_repository.py
prisma_web3_py/repositories/news_semantic_dedup_repository.py
prisma_web3_py/repositories/pre_signal_repository.py
prisma_web3_py/repositories/signal_repository.py
prisma_web3_py/repositories/token_repository.py
prisma_web3_py/utils/README.md
prisma_web3_py/utils/__init__.py
prisma_web3_py/utils/chain_config.py
prisma_web3_py/utils/datetime.py
prisma_web3_py/utils/token_importer.py
prisma_web3_py-1.0.46.dist-info/licenses/LICENSE
prisma_web3_py-1.0.46.dist-info/METADATA
prisma_web3_py-1.0.46.dist-info/WHEEL
prisma_web3_py-1.0.46.dist-info/top_level.txt
prisma_web3_py-1.0.46.dist-info/RECORD
