Metadata-Version: 2.4
Name: prisma-web3-py
Version: 1.0.46
Summary: Python/SQLAlchemy async implementation of Prisma Web3 database models
Home-page: https://github.com/your-org/prisma-web3
Author: SmallCat
Author-email: SmallCat <your-email@example.com>
License: MIT
Project-URL: Homepage, https://github.com/your-org/prisma-web3
Project-URL: Documentation, https://github.com/your-org/prisma-web3/tree/main/python
Project-URL: Repository, https://github.com/your-org/prisma-web3
Project-URL: Issues, https://github.com/your-org/prisma-web3/issues
Keywords: database,orm,sqlalchemy,async,web3,prisma
Classifier: Development Status :: 4 - Beta
Classifier: Intended Audience :: Developers
Classifier: Topic :: Database
Classifier: Programming Language :: Python :: 3
Classifier: Programming Language :: Python :: 3.8
Classifier: Programming Language :: Python :: 3.9
Classifier: Programming Language :: Python :: 3.10
Classifier: Programming Language :: Python :: 3.11
Classifier: Programming Language :: Python :: 3.12
Classifier: License :: OSI Approved :: MIT License
Classifier: Framework :: AsyncIO
Requires-Python: >=3.8
License-File: LICENSE
Requires-Dist: sqlalchemy>=2.0.0
Requires-Dist: asyncpg>=0.27.0
Requires-Dist: python-dotenv>=0.19.0
Provides-Extra: dev
Requires-Dist: pytest>=7.0.0; extra == "dev"
Requires-Dist: pytest-asyncio>=0.21.0; extra == "dev"
Requires-Dist: black>=23.0.0; extra == "dev"
Requires-Dist: mypy>=1.0.0; extra == "dev"
Dynamic: author
Dynamic: home-page
Dynamic: license-file
Dynamic: requires-python
